njupt/__init__.py
njupt/base.py
njupt/card.py
njupt/error.py
njupt/exceptions.py
njupt/library.py
njupt/runningman.py
njupt/settings.py
njupt/urls.py
njupt/zhengfang.py
njupt/decorators/__init__.py
njupt/decorators/card_logined.py
njupt/decorators/zhengfang_logined.py
njupt/models/__init__.py
njupt/models/aolan.py
njupt/models/base.py
njupt/models/card.py
njupt/models/zhengfang.py
njupt/utils/__init__.py
njupt/utils/aolan/__init__.py
njupt/utils/aolan/aolan_captcha.py
njupt/utils/aolan/get_sample_set.py
njupt/utils/aolan/imageset.dat
njupt/utils/aolan/train.py
njupt/utils/captchas/__init__.py
njupt/utils/captchas/aolan/__init__.py
njupt/utils/captchas/aolan/aolan_captcha.py
njupt/utils/captchas/aolan/get_sample_set.py
njupt/utils/captchas/aolan/image_data.json
njupt/utils/captchas/aolan/train.py
njupt/utils/captchas/card/__init__.py
njupt/utils/captchas/card/captcha_getter.py
njupt/utils/captchas/card/card_captcha.py
njupt/utils/captchas/card/gen_image_data.py
njupt/utils/captchas/card/image_data.json
njupt/utils/captchas/library/__init__.py
njupt/utils/captchas/library/gen_image_data.py
njupt/utils/captchas/library/image_data.json
njupt/utils/captchas/library/libray_captcha.py
njupt/utils/captchas/zhengfang/__init__.py
njupt/utils/captchas/zhengfang/captcha_getter.py
njupt/utils/captchas/zhengfang/gen_image_data.py
njupt/utils/captchas/zhengfang/image_data.json
njupt/utils/captchas/zhengfang/zhengfang_captcha.py
njupt/utils/card/__init__.py
njupt/utils/card/captcha_getter.py
njupt/utils/card/card_captcha.py
njupt/utils/card/imageset.dat
njupt/utils/card/train.py
njupt/utils/zhengfang/__init__.py
njupt/utils/zhengfang/captcha_getter.py
njupt/utils/zhengfang/imageset.dat
njupt/utils/zhengfang/train.py
njupt/utils/zhengfang/train_svm.py
njupt/utils/zhengfang/zhengfang_captcha.py
njupt/utils/zhengfang/zhengfang_captcha_svm.py
tests/test_zhengfang/__init__.py
tests/test_zhengfang/conftest.py
tests/test_zhengfang/zhengfang_test.py
njupt-0.2.3.dist-info/LICENSE
njupt-0.2.3.dist-info/METADATA
njupt-0.2.3.dist-info/WHEEL
njupt-0.2.3.dist-info/top_level.txt
njupt-0.2.3.dist-info/RECORD
