Metadata-Version: 2.1
Name: njupt
Version: 0.2.3
Summary: Python API Wrappers for NJUPT.
Home-page: https://github.com/gaoliang/NJUPT-API
Author: Gao Liang
Author-email: me@gaoliang.im
License: MIT
Platform: UNKNOWN
Classifier: License :: OSI Approved :: MIT License
Classifier: Programming Language :: Python
Classifier: Programming Language :: Python :: 3
Classifier: Programming Language :: Python :: 3.6
Classifier: Programming Language :: Python :: Implementation :: CPython
Classifier: Programming Language :: Python :: Implementation :: PyPy
Requires-Python: >=3.0.0
Requires-Dist: requests (>=2.20.0)
Requires-Dist: bs4
Requires-Dist: lxml
Requires-Dist: pillow
